.gitignore
LICENSE.md
README.md
pyproject.toml
.github/workflows/publish.yml
.github/workflows/test.yml
calico_bootstrap/__init__.py
calico_bootstrap/apps.py
calico_bootstrap.egg-info/PKG-INFO
calico_bootstrap.egg-info/SOURCES.txt
calico_bootstrap.egg-info/dependency_links.txt
calico_bootstrap.egg-info/entry_points.txt
calico_bootstrap.egg-info/requires.txt
calico_bootstrap.egg-info/top_level.txt
calico_bootstrap/templates/widgets/_author.scss
calico_bootstrap/templates/widgets/_back_to_top.scss
calico_bootstrap/templates/widgets/_blog_index.scss
calico_bootstrap/templates/widgets/_blog_post.scss
calico_bootstrap/templates/widgets/_footer_brand.scss
calico_bootstrap/templates/widgets/_footer_menu.scss
calico_bootstrap/templates/widgets/_footer_social.scss
calico_bootstrap/templates/widgets/_hero.scss
calico_bootstrap/templates/widgets/_light_switch.scss
calico_bootstrap/templates/widgets/_main_nav.scss
calico_bootstrap/templates/widgets/_section.scss
calico_bootstrap/templates/widgets/_separator.scss
calico_bootstrap/templates/widgets/_tags_list.scss
calico_bootstrap/templates/widgets/_team.scss
calico_bootstrap/templates/widgets/_text.scss
calico_bootstrap/templates/widgets/author.html
calico_bootstrap/templates/widgets/back_to_top.html
calico_bootstrap/templates/widgets/blog_index.html
calico_bootstrap/templates/widgets/blog_post.html
calico_bootstrap/templates/widgets/footer_brand.html
calico_bootstrap/templates/widgets/footer_menu.html
calico_bootstrap/templates/widgets/footer_social.html
calico_bootstrap/templates/widgets/hero.html
calico_bootstrap/templates/widgets/light_switch.html
calico_bootstrap/templates/widgets/main_nav.html
calico_bootstrap/templates/widgets/post_excerpt.html
calico_bootstrap/templates/widgets/redirect.html
calico_bootstrap/templates/widgets/section.html
calico_bootstrap/templates/widgets/separator.html
calico_bootstrap/templates/widgets/tags_list.html
calico_bootstrap/templates/widgets/team.html
calico_bootstrap/templates/widgets/text.html
tests/test_calico_bootstrap.py
tests/test_project/__init__.py
tests/test_project/settings.py
tests/test_project/urls.py