Metadata-Version: 2.4
Name: calico-bootstrap
Version: 0.1
Summary: Bootstrap theme for Calico SSG
Author: Emma Delescolle
License: MIT
Project-URL: Homepage, https://calico-ssg.com
Project-URL: Issues, https://gitlab.levitnet.be/levit/calico-bootstrap/-/issues
Classifier: Framework :: Django :: 5
Classifier: License :: OSI Approved :: MIT License
License-File: LICENSE.md
Requires-Dist: calico_ssg
Provides-Extra: test
Dynamic: license-file
